{
  "kind": "collectionType",
  "collectionName": "notice",
  "info": {
    "singularName": "notices",
    "pluralName": "notice",
    "displayName": "Notices",
    "description": ""
  },
  "options": {
    "draftAndPublish": true
  },
  "pluginOptions": {},
  "attributes": {
    "title": {
      "type": "text"
    },
    "date": {
      "type": "date"
    },
    "pdf": {
      "type": "media",
      "multiple": true,
      "required": false,
      "allowedTypes": [
        "images",
        "files",
        "videos",
        "audios"
      ]
    }
  }
}
